logria/__init__.py
logria/__main__.py
logria/commands/__init__.py
logria/commands/command.py
logria/commands/config.py
logria/commands/edit.py
logria/commands/parser.py
logria/commands/regex.py
logria/commands/scroll.py
logria/commands/window.py
logria/communication/__init__.py
logria/communication/input_handler.py
logria/communication/input_history.py
logria/communication/render.py
logria/communication/setup.py
logria/communication/shell_output.py
logria/interface/__init__.py
logria/interface/color_handler.py
logria/interface/textbox.py
logria/logger/__init__.py
logria/logger/default_logger.py
logria/logger/parser.py
logria/logger/processor.py
logria/utilities/__init__.py
logria/utilities/command_parser.py
logria/utilities/constants.py
logria/utilities/fs.py
logria/utilities/keystrokes.py
logria/utilities/regex_generator.py
logria/utilities/session.py
tests/__init__.py
tests/test_app_launch.py
tests/test_color_handler.py
tests/test_command_parser.py
tests/test_constants.py
tests/test_fs.py
tests/test_history_tape.py
tests/test_input_handler.py
tests/test_keystrokes.py
tests/test_parser.py
tests/test_processors.py
tests/test_regex_generator.py
tests/test_render_position.py
tests/test_resolve_delete.py
tests/test_session.py
Logria-0.9.14.dist-info/LICENSE
Logria-0.9.14.dist-info/METADATA
Logria-0.9.14.dist-info/WHEEL
Logria-0.9.14.dist-info/entry_points.txt
Logria-0.9.14.dist-info/top_level.txt
Logria-0.9.14.dist-info/RECORD
