Metadata-Version: 2.1
Name: Logria
Version: 0.9.14
Summary: A powerful CLI tool that puts log analytics at your fingertips.
Home-page: https://github.com/ReagentX/Logria-py
Author: Christopher Sardegna
Author-email: logria@reagentx.net
License: UNKNOWN
Platform: UNKNOWN
Classifier: Development Status :: 4 - Beta
Classifier: Environment :: Console :: Curses
Classifier: License :: OSI Approved :: GNU General Public License v3 or later (GPLv3+)
Classifier: Natural Language :: English
Classifier: Operating System :: OS Independent
Classifier: Programming Language :: Python :: 3.8
Classifier: Topic :: System :: Logging
Classifier: Topic :: Internet :: Log Analysis
Classifier: Topic :: Software Development :: Libraries :: Python Modules
Requires-Python: >=3.6
